{
  "taskId": 1755413841796,
  "projectId": "Z-004",
  "projectTitle": "Landing Page for 2Baba 40-Year Concert",
  "organizationId": 4,
  "projectTypeTags": [
    "Frontend Development",
    "UI/UX Design"
  ],
  "title": "Testing & Launch",
  "status": "Approved",
  "completed": true,
  "order": 3,
  "link": "bit.ly23434",
  "dueDate": "2025-08-17T00:00:00.000Z",
  "rejected": false,
  "feedbackCount": 0,
  "pushedBack": false,
  "version": 1,
  "description": "Optimize for performance, test across devices, and deliver a polished page ready for live ticket sales.",
  "submittedDate": "2025-08-17T06:54:00.552Z",
  "approvedDate": "2025-08-17T06:59:55.563Z",
  "createdDate": "2025-08-17T06:51:19.657Z",
  "lastModified": "2025-08-17T06:59:55.563Z"
}