{
  "taskId": 1756238331779,
  "projectId": "C-011",
  "projectTitle": "90% Completion Landing Page Win ",
  "organizationId": 3,
  "projectTypeTags": [],
  "title": "Phase 1 ",
  "status": "Approved",
  "completed": true,
  "order": 1,
  "link": "bit.ly234324",
  "dueDate": "2025-08-28T04:00:00.000Z",
  "rejected": false,
  "feedbackCount": 0,
  "pushedBack": false,
  "version": 1,
  "description": "Collaborate with our team to understand brand values, audience, and aesthetic direction. Deliver moodboards, style frames, and an adaptable design system aligned with Web3 culture.\n\n",
  "submittedDate": "2025-08-26T19:52:01.829Z",
  "createdDate": "2025-08-26T19:50:54.749Z",
  "lastModified": "2025-08-26T19:52:31.994Z",
  "manualInvoiceEligible": true,
  "invoicePaid": false,
  "approvedBy": 34,
  "approvedAt": "2025-08-26T19:52:31.993Z"
}